napalm_hios/__init__.py
napalm_hios/hios.py
napalm_hios/mock_hios_device.py
napalm_hios/netconf_hios.py
napalm_hios/snmp_hios.py
napalm_hios/ssh_hios.py
napalm_hios/utils.py
napalm_hios/version.py
napalm_hios-1.0.2.dist-info/AUTHORS
napalm_hios-1.0.2.dist-info/LICENSE
napalm_hios-1.0.2.dist-info/METADATA
napalm_hios-1.0.2.dist-info/WHEEL
napalm_hios-1.0.2.dist-info/entry_points.txt
napalm_hios-1.0.2.dist-info/top_level.txt
napalm_hios-1.0.2.dist-info/RECORD
