Metadata-Version: 2.1
Name: napalm-hios
Version: 1.0.2
Summary: NAPALM driver for HiOS network switches by Belden
Home-page: https://github.com/yourusername/napalm-hios
Author: Your Name
Author-email: your.email@example.com
Classifier: Programming Language :: Python :: 3
Classifier: License :: OSI Approved :: Apache Software License
Classifier: Operating System :: OS Independent
Requires-Python: >=3.7
License-File: LICENSE
License-File: AUTHORS
Requires-Dist: napalm >=3.0.0
Requires-Dist: ncclient >=0.6.9
Requires-Dist: netmiko >=3.3.0
Requires-Dist: pysnmp >=4.4.12
